{
  "nodes": [
    {
      "id": 19
    },
    {
      "id": 9
    },
    {
      "id": 11
    },
    {
      "id": 14
    },
    {
      "id": 22
    },
    {
      "id": 25
    },
    {
      "id": 29
    },
    {
      "id": 38
    }
  ],
  "links": [
    {
      "id": 27,
      "source": 19,
      "target": 22
    },
    {
      "id": 28,
      "source": 19,
      "target": 25
    },
    {
      "id": 40,
      "source": 9,
      "target": 14
    },
    {
      "id": 41,
      "source": 9,
      "target": 38
    },
    {
      "id": 42,
      "source": 11,
      "target": 29
    }
  ]
}