{
    "directed": false,
    "multigraph": false,
    "graph": {
        "node_default": {},
        "edge_default": {}
    },
    "nodes": [
        {
            "id": "n0"
        },
        {
            "id": "n1"
        },
        {
            "id": "n2"
        },
        {
            "id": "n3"
        },
        {
            "id": "n4"
        },
        {
            "id": "n5"
        },
        {
            "id": "n6"
        },
        {
            "id": "n7"
        },
        {
            "id": "n8"
        },
        {
            "id": "n9"
        },
        {
            "id": "n10"
        },
        {
            "id": "n11"
        },
        {
            "id": "n12"
        },
        {
            "id": "n13"
        },
        {
            "id": "n14"
        },
        {
            "id": "n15"
        },
        {
            "id": "n16"
        },
        {
            "id": "n17"
        },
        {
            "id": "n18"
        },
        {
            "id": "n19"
        }
    ],
    "links": [
        {
            "id": "e3",
            "source": "n0",
            "target": "n8"
        },
        {
            "id": "e5",
            "source": "n0",
            "target": "n15"
        },
        {
            "id": "e9",
            "source": "n0",
            "target": "n12"
        },
        {
            "id": "e13",
            "source": "n0",
            "target": "n16"
        },
        {
            "id": "e19",
            "source": "n0",
            "target": "n17"
        },
        {
            "id": "e0",
            "source": "n1",
            "target": "n8"
        },
        {
            "id": "e2",
            "source": "n1",
            "target": "n9"
        },
        {
            "id": "e1",
            "source": "n2",
            "target": "n8"
        },
        {
            "id": "e18",
            "source": "n3",
            "target": "n17"
        },
        {
            "id": "e4",
            "source": "n4",
            "target": "n10"
        },
        {
            "id": "e8",
            "source": "n5",
            "target": "n12"
        },
        {
            "id": "e10",
            "source": "n5",
            "target": "n11"
        },
        {
            "id": "e20",
            "source": "n5",
            "target": "n17"
        },
        {
            "id": "e24",
            "source": "n5",
            "target": "n19"
        },
        {
            "id": "e6",
            "source": "n6",
            "target": "n15"
        },
        {
            "id": "e7",
            "source": "n6",
            "target": "n13"
        },
        {
            "id": "e11",
            "source": "n6",
            "target": "n14"
        },
        {
            "id": "e12",
            "source": "n7",
            "target": "n14"
        },
        {
            "id": "e17",
            "source": "n7",
            "target": "n17"
        },
        {
            "id": "e16",
            "source": "n9",
            "target": "n17"
        },
        {
            "id": "e14",
            "source": "n10",
            "target": "n16"
        },
        {
            "id": "e23",
            "source": "n11",
            "target": "n18"
        },
        {
            "id": "e21",
            "source": "n15",
            "target": "n17"
        },
        {
            "id": "e15",
            "source": "n16",
            "target": "n17"
        },
        {
            "id": "e22",
            "source": "n17",
            "target": "n18"
        }
    ]
}